ommx-2.3.4.dist-info/METADATA
ommx-2.3.4.dist-info/WHEEL
ommx/mps.py
ommx/dataset.py
ommx/adapter.py
ommx/artifact.py
ommx/_ommx_rust.pyi
ommx/py.typed
ommx/testing.py
ommx/v1/constraint_hints_pb2.py
ommx/v1/parametric_instance_pb2.py
ommx/v1/function_pb2.py
ommx/v1/solution_pb2.pyi
ommx/v1/parametric_instance_pb2.pyi
ommx/v1/decision_variables_pb2.py
ommx/v1/polynomial_pb2.py
ommx/v1/sos1_pb2.py
ommx/v1/linear_pb2.py
ommx/v1/linear_pb2.pyi
ommx/v1/sample_set_pb2.py
ommx/v1/annotation.py
ommx/v1/function_pb2.pyi
ommx/v1/constraint_pb2.pyi
ommx/v1/quadratic_pb2.py
ommx/v1/constraint_hints_pb2.pyi
ommx/v1/sos1_pb2.pyi
ommx/v1/decision_variables_pb2.pyi
ommx/v1/solution_pb2.py
ommx/v1/one_hot_pb2.pyi
ommx/v1/sample_set_pb2.pyi
ommx/v1/quadratic_pb2.pyi
ommx/v1/instance_pb2.pyi
ommx/v1/one_hot_pb2.py
ommx/v1/__init__.py
ommx/v1/polynomial_pb2.pyi
ommx/v1/constraint_pb2.py
ommx/v1/instance_pb2.py
ommx/__init__.py
ommx/qplib.py
ommx/_ommx_rust.cpython-314t-x86_64-linux-gnu.so
ommx-2.3.4.dist-info/RECORD
