Metadata-Version: 2.4
Name: ommx
Version: 2.3.4
Classifier: Programming Language :: Python :: 3 :: Only
Classifier: Programming Language :: Python :: 3.10
Classifier: Programming Language :: Python :: 3.11
Classifier: Programming Language :: Python :: 3.12
Classifier: Programming Language :: Python :: 3.13
Classifier: Programming Language :: Python :: 3.14
Classifier: Programming Language :: Rust
Classifier: Programming Language :: Python :: Implementation :: CPython
Classifier: Programming Language :: Python :: Implementation :: PyPy
Classifier: License :: OSI Approved :: Apache Software License
Classifier: License :: OSI Approved :: MIT License
Requires-Dist: numpy>=1.23.0,<3.0.0
Requires-Dist: pandas>=2.0.0,<3.0.0
Requires-Dist: protobuf>=5.26.1,<6.0.0
Requires-Dist: pyarrow>=16.0.0,<23.0.0
Requires-Dist: python-dateutil>=2.9.0,<3.0.0
Requires-Dist: typing-extensions>=4.12.2,<5.0.0
Summary: Open Mathematical prograMming eXchange (OMMX)
Author-email: "Jij Inc." <info@j-ij.com>
License: MIT OR Apache-2.0
Requires-Python: >=3.10
Project-URL: Repository, https://github.com/Jij-Inc/ommx
Project-URL: Issues, https://github.com/Jij-Inc/ommx/issues
